{
  "players": {
    "3ded4e81-be86-43c2-a8eb-896f44d223d1": {
      "profiles": {
        "kiwi": {
          "sackContents": {
            "ENCHANTED_MITHRIL": {
              "amount": 6919,
              "lastChange": 0,
              "status": "CORRECT"
            },
            "ENCHANTED_TITANIUM": {
              "amount": 677,
              "lastChange": 0,
              "status": "CORRECT"
            },
            "ENCHANTED_SUGAR": {
              "amount": 2493,
              "lastChange": 0,
              "status": "CORRECT"
            },
            "ENCHANTED_POTATO": {
              "amount": 71,
              "lastChange": 0,
              "status": "CORRECT"
            },
            "ENCHANTED_MELON": {
              "amount": 143,
              "lastChange": -640,
              "status": "CORRECT"
            },
            "ENCHANTED_HAY_BLOCK": {
              "amount": 14,
              "lastChange": 0,
              "status": "CORRECT"
            },
            "ENCHANTED_PUMPKIN": {
              "amount": 796,
              "lastChange": 8,
              "status": "CORRECT"
            },
            "ENCHANTED_COCOA": {
              "amount": 84,
              "lastChange": 8,
              "status": "CORRECT"
            },
            "ENCHANTED_NETHER_STALK": {
              "amount": 2489,
              "lastChange": -546,
              "status": "CORRECT"
            },
            "ENCHANTED_BAKED_POTATO": {
              "amount": 2,
              "lastChange": 0,
              "status": "CORRECT"
            },
            "ENCHANTED_BROWN_MUSHROOM": {
              "amount": 344,
              "lastChange": 3,
              "status": "CORRECT"
            },
            "ENCHANTED_CACTUS_GREEN": {
              "amount": 63,
              "lastChange": -175,
              "status": "CORRECT"
            },
            "ENCHANTED_RED_MUSHROOM": {
              "amount": 177,
              "lastChange": 2,
              "status": "CORRECT"
            },
            "NETHER_STALK": {
              "amount": 20159,
              "lastChange": 0,
              "status": "CORRECT"
            },
            "BOX_OF_SEEDS": {
              "amount": 0,
              "lastChange": 0,
              "status": "CORRECT"
            },
            "ENCHANTED_BREAD": {
              "amount": 0,
              "lastChange": 0,
              "status": "CORRECT"
            },
            "ENCHANTED_HUGE_MUSHROOM_1": {
              "amount": 56,
              "lastChange": 0,
              "status": "CORRECT"
            },
            "ENCHANTED_CACTUS": {
              "amount": 1,
              "lastChange": 0,
              "status": "CORRECT"
            },
            "ENCHANTED_CARROT": {
              "amount": 304,
              "lastChange": 0,
              "status": "CORRECT"
            },
            "ENCHANTED_COOKIE": {
              "amount": 1,
              "lastChange": 0,
              "status": "CORRECT"
            },
            "ENCHANTED_GOLDEN_CARROT": {
              "amount": 1,
              "lastChange": 0,
              "status": "CORRECT"
            },
            "ENCHANTED_MELON_BLOCK": {
              "amount": 0,
              "lastChange": -4,
              "status": "CORRECT"
            },
            "ENCHANTED_POISONOUS_POTATO": {
              "amount": 0,
              "lastChange": 0,
              "status": "CORRECT"
            },
            "ENCHANTED_HUGE_MUSHROOM_2": {
              "amount": 93,
              "lastChange": 0,
              "status": "CORRECT"
            },
            "ENCHANTED_SEEDS": {
              "amount": 73,
              "lastChange": -320,
              "status": "CORRECT"
            },
            "ENCHANTED_SUGAR_CANE": {
              "amount": 0,
              "lastChange": 0,
              "status": "CORRECT"
            },
            "MUTANT_NETHER_STALK": {
              "amount": 3,
              "lastChange": 0,
              "status": "CORRECT"
            },
            "POLISHED_PUMPKIN": {
              "amount": 0,
              "lastChange": 0,
              "status": "CORRECT"
            },
            "TIGHTLY_TIED_HAY_BALE": {
              "amount": 0,
              "lastChange": 0,
              "status": "CORRECT"
            },
            "MITHRIL_ORE": {
              "amount": 20160,
              "lastChange": 0,
              "status": "CORRECT"
            },
            "TITANIUM_ORE": {
              "amount": 20160,
              "lastChange": 0,
              "status": "CORRECT"
            },
            "POTATO_ITEM": {
              "amount": 20159,
              "lastChange": 0,
              "status": "CORRECT"
            },
            "COMPOST": {
              "amount": 1,
              "lastChange": 0,
              "status": "CORRECT"
            },
            "CONCENTRATED_STONE": {
              "amount": 0,
              "lastChange": 0,
              "status": "CORRECT"
            },
            "ENCHANTED_COAL": {
              "amount": 11,
              "lastChange": 0,
              "status": "CORRECT"
            },
            "ENCHANTED_COAL_BLOCK": {
              "amount": 4,
              "lastChange": 0,
              "status": "CORRECT"
            },
            "ENCHANTED_COBBLESTONE": {
              "amount": 7,
              "lastChange": 0,
              "status": "CORRECT"
            },
            "ENCHANTED_DIAMOND": {
              "amount": 75,
              "lastChange": 0,
              "status": "CORRECT"
            },
            "ENCHANTED_DIAMOND_BLOCK": {
              "amount": 0,
              "lastChange": 0,
              "status": "CORRECT"
            },
            "ENCHANTED_EMERALD": {
              "amount": 0,
              "lastChange": 0,
              "status": "CORRECT"
            },
            "ENCHANTED_EMERALD_BLOCK": {
              "amount": 0,
              "lastChange": 0,
              "status": "CORRECT"
            },
            "ENCHANTED_ENDSTONE": {
              "amount": 24,
              "lastChange": 0,
              "status": "CORRECT"
            },
            "ENCHANTED_FLINT": {
              "amount": 0,
              "lastChange": 0,
              "status": "CORRECT"
            },
            "ENCHANTED_GLACITE": {
              "amount": 166,
              "lastChange": 0,
              "status": "CORRECT"
            },
            "ENCHANTED_GLOWSTONE": {
              "amount": 0,
              "lastChange": 0,
              "status": "CORRECT"
            },
            "ENCHANTED_GLOWSTONE_DUST": {
              "amount": 0,
              "lastChange": 0,
              "status": "CORRECT"
            },
            "ENCHANTED_GOLD": {
              "amount": 222,
              "lastChange": 0,
              "status": "CORRECT"
            },
            "ENCHANTED_GOLD_BLOCK": {
              "amount": 0,
              "lastChange": 0,
              "status": "CORRECT"
            },
            "ENCHANTED_HARD_STONE": {
              "amount": 1290,
              "lastChange": 1,
              "status": "CORRECT"
            },
            "ENCHANTED_IRON": {
              "amount": 243,
              "lastChange": 0,
              "status": "CORRECT"
            },
            "ENCHANTED_IRON_BLOCK": {
              "amount": 0,
              "lastChange": 0,
              "status": "CORRECT"
            },
            "ENCHANTED_LAPIS_LAZULI_BLOCK": {
              "amount": 0,
              "lastChange": 0,
              "status": "CORRECT"
            },
            "ENCHANTED_LAPIS_LAZULI": {
              "amount": 0,
              "lastChange": 0,
              "status": "CORRECT"
            },
            "ENCHANTED_MYCELIUM": {
              "amount": 0,
              "lastChange": 0,
              "status": "CORRECT"
            },
            "ENCHANTED_MYCELIUM_CUBE": {
              "amount": 0,
              "lastChange": 0,
              "status": "CORRECT"
            },
            "ENCHANTED_NETHERRACK": {
              "amount": 0,
              "lastChange": 0,
              "status": "CORRECT"
            },
            "ENCHANTED_OBSIDIAN": {
              "amount": 5,
              "lastChange": 0,
              "status": "CORRECT"
            },
            "ENCHANTED_QUARTZ": {
              "amount": 0,
              "lastChange": 0,
              "status": "CORRECT"
            },
            "ENCHANTED_QUARTZ_BLOCK": {
              "amount": 0,
              "lastChange": 0,
              "status": "CORRECT"
            },
            "ENCHANTED_RED_SAND": {
              "amount": 25,
              "lastChange": 0,
              "status": "CORRECT"
            },
            "ENCHANTED_RED_SAND_CUBE": {
              "amount": 0,
              "lastChange": 0,
              "status": "CORRECT"
            },
            "ENCHANTED_REDSTONE": {
              "amount": 0,
              "lastChange": 0,
              "status": "CORRECT"
            },
            "ENCHANTED_REDSTONE_BLOCK": {
              "amount": 0,
              "lastChange": 0,
              "status": "CORRECT"
            },
            "ENCHANTED_SAND": {
              "amount": 0,
              "lastChange": 0,
              "status": "CORRECT"
            },
            "ENCHANTED_SULPHUR": {
              "amount": 0,
              "lastChange": 0,
              "status": "CORRECT"
            },
            "ENCHANTED_SULPHUR_CUBE": {
              "amount": 0,
              "lastChange": 0,
              "status": "CORRECT"
            },
            "ENCHANTED_TUNGSTEN": {
              "amount": 31,
              "lastChange": 0,
              "status": "CORRECT"
            },
            "ENCHANTED_UMBER": {
              "amount": 79,
              "lastChange": 0,
              "status": "CORRECT"
            },
            "COAL": {
              "amount": 6776,
              "lastChange": 1701,
              "status": "CORRECT"
            },
            "COBBLESTONE": {
              "amount": 6133,
              "lastChange": 0,
              "status": "CORRECT"
            },
            "DIAMOND": {
              "amount": 20160,
              "lastChange": 0,
              "status": "CORRECT"
            },
            "EMERALD": {
              "amount": 9889,
              "lastChange": 232,
              "status": "CORRECT"
            },
            "ENDER_STONE": {
              "amount": 9,
              "lastChange": 0,
              "status": "CORRECT"
            },
            "FLINT": {
              "amount": 0,
              "lastChange": 0,
              "status": "CORRECT"
            },
            "GLACITE": {
              "amount": 20160,
              "lastChange": 0,
              "status": "CORRECT"
            },
            "GLOSSY_GEMSTONE": {
              "amount": 0,
              "lastChange": 0,
              "status": "CORRECT"
            },
            "GLOWSTONE_DUST": {
              "amount": 0,
              "lastChange": 0,
              "status": "CORRECT"
            },
            "GOLD_INGOT": {
              "amount": 84,
              "lastChange": 0,
              "status": "CORRECT"
            },
            "GRAVEL": {
              "amount": 0,
              "lastChange": 0,
              "status": "CORRECT"
            },
            "HARD_STONE": {
              "amount": 558,
              "lastChange": 82,
              "status": "CORRECT"
            },
            "IRON_INGOT": {
              "amount": 10298,
              "lastChange": 84,
              "status": "CORRECT"
            },
            "INK_SACK-4": {
              "amount": 17557,
              "lastChange": 261,
              "status": "CORRECT"
            },
            "MYCEL": {
              "amount": 205,
              "lastChange": 0,
              "status": "CORRECT"
            },
            "QUARTZ": {
              "amount": 0,
              "lastChange": 0,
              "status": "CORRECT"
            },
            "NETHERRACK": {
              "amount": 5,
              "lastChange": 0,
              "status": "CORRECT"
            },
            "OBSIDIAN": {
              "amount": 2191,
              "lastChange": 0,
              "status": "CORRECT"
            },
            "OIL_BARREL": {
              "amount": 271,
              "lastChange": 1,
              "status": "CORRECT"
            },
            "PLASMA": {
              "amount": 0,
              "lastChange": 0,
              "status": "CORRECT"
            },
            "SAND-1": {
              "amount": 19319,
              "lastChange": 0,
              "status": "CORRECT"
            },
            "REDSTONE": {
              "amount": 17913,
              "lastChange": 721,
              "status": "CORRECT"
            },
            "REFINED_MINERAL": {
              "amount": 1,
              "lastChange": 0,
              "status": "CORRECT"
            },
            "SAND": {
              "amount": 126,
              "lastChange": 0,
              "status": "CORRECT"
            },
            "STARFALL": {
              "amount": 41,
              "lastChange": 0,
              "status": "CORRECT"
            },
            "STONE": {
              "amount": 20160,
              "lastChange": 0,
              "status": "CORRECT"
            },
            "TREASURITE": {
              "amount": 17,
              "lastChange": 0,
              "status": "CORRECT"
            },
            "TUNGSTEN": {
              "amount": 14169,
              "lastChange": 0,
              "status": "CORRECT"
            },
            "UMBER": {
              "amount": 20160,
              "lastChange": 0,
              "status": "CORRECT"
            },
            "VOLTA": {
              "amount": 0,
              "lastChange": 0,
              "status": "CORRECT"
            },
            "ROUGH_JADE_GEM": {
              "amount": 10767,
              "lastChange": 757,
              "status": "CORRECT"
            },
            "ROUGH_TOPAZ_GEM": {
              "amount": 4490,
              "lastChange": 15,
              "status": "CORRECT"
            },
            "ROUGH_AMBER_GEM": {
              "amount": 3666,
              "lastChange": 48,
              "status": "CORRECT"
            },
            "INK_SACK-3": {
              "amount": 20159,
              "lastChange": 0,
              "status": "CORRECT"
            },
            "WHEAT": {
              "amount": 20160,
              "lastChange": 0,
              "status": "CORRECT"
            },
            "CARROT_ITEM": {
              "amount": 20157,
              "lastChange": -2,
              "status": "CORRECT"
            },
            "ROUGH_RUBY_GEM": {
              "amount": 2736,
              "lastChange": 0,
              "status": "CORRECT"
            },
            "FLAWED_AMBER_GEM": {
              "amount": 536,
              "lastChange": 12,
              "status": "CORRECT"
            },
            "FLAWED_RUBY_GEM": {
              "amount": 49,
              "lastChange": 18,
              "status": "CORRECT"
            },
            "HAY_BALE": {
              "amount": 28,
              "lastChange": -7200,
              "status": "OUTDATED"
            },
            "SEEDS": {
              "amount": 20159,
              "lastChange": -1,
              "status": "CORRECT"
            },
            "GOLDEN_CARROT": {
              "amount": 6912,
              "lastChange": 0,
              "status": "CORRECT"
            },
            "BROWN_MUSHROOM": {
              "amount": 20160,
              "lastChange": 0,
              "status": "CORRECT"
            },
            "CACTUS": {
              "amount": 16,
              "lastChange": 0,
              "status": "CORRECT"
            },
            "INK_SACK-2": {
              "amount": 20160,
              "lastChange": 0,
              "status": "CORRECT"
            },
            "CROPIE": {
              "amount": 0,
              "lastChange": 0,
              "status": "CORRECT"
            },
            "HAY_BLOCK": {
              "amount": 116,
              "lastChange": 0,
              "status": "CORRECT"
            },
            "MELON": {
              "amount": 20160,
              "lastChange": 64,
              "status": "CORRECT"
            },
            "POISONOUS_POTATO": {
              "amount": 1,
              "lastChange": 0,
              "status": "CORRECT"
            },
            "PUMPKIN": {
              "amount": 20160,
              "lastChange": 0,
              "status": "CORRECT"
            },
            "RED_MUSHROOM": {
              "amount": 20160,
              "lastChange": 0,
              "status": "CORRECT"
            },
            "SQUASH": {
              "amount": 0,
              "lastChange": 0,
              "status": "CORRECT"
            },
            "SUGAR_CANE": {
              "amount": 19616,
              "lastChange": -128,
              "status": "CORRECT"
            },
            "CRUDE_GABAGOOL": {
              "amount": 0,
              "lastChange": 0,
              "status": "CORRECT"
            },
            "DERELICT_ASHE": {
              "amount": 0,
              "lastChange": 0,
              "status": "CORRECT"
            },
            "NULL_ATOM": {
              "amount": 0,
              "lastChange": 0,
              "status": "CORRECT"
            },
            "NULL_SPHERE": {
              "amount": 324,
              "lastChange": 0,
              "status": "CORRECT"
            },
            "RAW_SOULFLOW": {
              "amount": 0,
              "lastChange": 0,
              "status": "CORRECT"
            },
            "REVENANT_CATALYST": {
              "amount": 0,
              "lastChange": 0,
              "status": "CORRECT"
            },
            "REVENANT_FLESH": {
              "amount": 0,
              "lastChange": 0,
              "status": "CORRECT"
            },
            "SOULFLOW": {
              "amount": 0,
              "lastChange": 0,
              "status": "CORRECT"
            },
            "SPIDER_CATALYST": {
              "amount": 0,
              "lastChange": 0,
              "status": "CORRECT"
            },
            "TARANTULA_WEB": {
              "amount": 0,
              "lastChange": 0,
              "status": "CORRECT"
            },
            "UNDEAD_CATALYST": {
              "amount": 0,
              "lastChange": 0,
              "status": "CORRECT"
            },
            "WOLF_TOOTH": {
              "amount": 1291,
              "lastChange": 0,
              "status": "CORRECT"
            },
            "BLAZE_ROD": {
              "amount": 20,
              "lastChange": 16,
              "status": "CORRECT"
            },
            "BONE": {
              "amount": 273,
              "lastChange": 0,
              "status": "CORRECT"
            },
            "CHILI_PEPPER": {
              "amount": 0,
              "lastChange": 0,
              "status": "CORRECT"
            },
            "ENDER_PEARL": {
              "amount": 6719,
              "lastChange": 15,
              "status": "CORRECT"
            },
            "GHAST_TEAR": {
              "amount": 0,
              "lastChange": 0,
              "status": "CORRECT"
            },
            "SULPHUR": {
              "amount": 24,
              "lastChange": 1,
              "status": "CORRECT"
            },
            "MAGMA_CREAM": {
              "amount": 208,
              "lastChange": 0,
              "status": "CORRECT"
            },
            "ROTTEN_FLESH": {
              "amount": 17,
              "lastChange": 2,
              "status": "CORRECT"
            },
            "SLIME_BALL": {
              "amount": 0,
              "lastChange": 0,
              "status": "CORRECT"
            },
            "SPIDER_EYE": {
              "amount": 0,
              "lastChange": 0,
              "status": "CORRECT"
            },
            "STRING": {
              "amount": 3,
              "lastChange": 0,
              "status": "CORRECT"
            },
            "ROUGH_SAPPHIRE_GEM": {
              "amount": 72,
              "lastChange": 30,
              "status": "CORRECT"
            },
            "FLAWED_JASPER_GEM": {
              "amount": 41,
              "lastChange": 12,
              "status": "CORRECT"
            },
            "ROUGH_JASPER_GEM": {
              "amount": 706,
              "lastChange": 0,
              "status": "CORRECT"
            },
            "FINE_AQUAMARINE_GEM": {
              "amount": 14,
              "lastChange": 1,
              "status": "CORRECT"
            },
            "FINE_CITRINE_GEM": {
              "amount": 19,
              "lastChange": 0,
              "status": "CORRECT"
            },
            "FINE_ONYX_GEM": {
              "amount": 12,
              "lastChange": 1,
              "status": "CORRECT"
            },
            "FLAWED_AQUAMARINE_GEM": {
              "amount": 1150,
              "lastChange": 45,
              "status": "CORRECT"
            },
            "FINE_PERIDOT_GEM": {
              "amount": 21,
              "lastChange": 2,
              "status": "CORRECT"
            },
            "FLAWED_TOPAZ_GEM": {
              "amount": 402,
              "lastChange": 24,
              "status": "CORRECT"
            },
            "FLAWED_JADE_GEM": {
              "amount": 845,
              "lastChange": 36,
              "status": "CORRECT"
            },
            "FLAWED_CITRINE_GEM": {
              "amount": 1776,
              "lastChange": 45,
              "status": "CORRECT"
            },
            "FLAWED_ONYX_GEM": {
              "amount": 907,
              "lastChange": 45,
              "status": "CORRECT"
            },
            "FINE_TOPAZ_GEM": {
              "amount": 2,
              "lastChange": 1,
              "status": "CORRECT"
            },
            "FLAWED_PERIDOT_GEM": {
              "amount": 740,
              "lastChange": 75,
              "status": "CORRECT"
            },
            "FLAWED_AMETHYST_GEM": {
              "amount": 101,
              "lastChange": 6,
              "status": "CORRECT"
            },
            "ROUGH_AMETHYST_GEM": {
              "amount": 277,
              "lastChange": 80,
              "status": "CORRECT"
            },
            "FLAWED_SAPPHIRE_GEM": {
              "amount": 102,
              "lastChange": 52,
              "status": "CORRECT"
            },
            "ROUGH_AQUAMARINE_GEM": {
              "amount": 18888,
              "lastChange": 1815,
              "status": "CORRECT"
            },
            "ROUGH_CITRINE_GEM": {
              "amount": 20553,
              "lastChange": 585,
              "status": "CORRECT"
            },
            "ROUGH_ONYX_GEM": {
              "amount": 11676,
              "lastChange": 2389,
              "status": "CORRECT"
            },
            "FINE_SAPPHIRE_GEM": {
              "amount": 69,
              "lastChange": 1,
              "status": "CORRECT"
            },
            "FINE_RUBY_GEM": {
              "amount": 23,
              "lastChange": 1,
              "status": "CORRECT"
            },
            "FINE_AMETHYST_GEM": {
              "amount": 95,
              "lastChange": 1,
              "status": "CORRECT"
            },
            "FINE_JADE_GEM": {
              "amount": 46,
              "lastChange": 1,
              "status": "CORRECT"
            },
            "FINE_AMBER_GEM": {
              "amount": 2,
              "lastChange": 1,
              "status": "CORRECT"
            },
            "FINE_JASPER_GEM": {
              "amount": 2,
              "lastChange": 1,
              "status": "CORRECT"
            },
            "ROUGH_OPAL_GEM": {
              "amount": 74,
              "lastChange": 0,
              "status": "CORRECT"
            },
            "FLAWED_OPAL_GEM": {
              "amount": 43,
              "lastChange": 0,
              "status": "CORRECT"
            },
            "FINE_OPAL_GEM": {
              "amount": 0,
              "lastChange": 0,
              "status": "CORRECT"
            },
            "ROUGH_PERIDOT_GEM": {
              "amount": 7472,
              "lastChange": 360,
              "status": "CORRECT"
            }
          }
        }
      }
    }
  }
}